__init__.py
calculator.py
calculator_module-0.0.2.dist-info/LICENCE
calculator_module-0.0.2.dist-info/METADATA
calculator_module-0.0.2.dist-info/WHEEL
calculator_module-0.0.2.dist-info/top_level.txt
calculator_module-0.0.2.dist-info/RECORD
