Metadata-Version: 2.1
Name: calculator-module
Version: 0.0.2
Summary: A simple arithmetic calculator package
Author: Minase Fikadu
Classifier: Programming Language :: Python :: 3
Classifier: License :: OSI Approved :: MIT License
Classifier: Operating System :: OS Independent
Requires-Python: >=3.8
License-File: LICENCE
